testplates/__init__.py
testplates/__version__.py
testplates/constraints.py
testplates/exceptions.py
testplates/py.typed
testplates/structure.py
testplates/validators.py
testplates/value.py
testplates/impl/__init__.py
testplates/impl/utils.py
testplates/impl/base/__init__.py
testplates/impl/base/boundaries.py
testplates/impl/base/exceptions.py
testplates/impl/base/limit.py
testplates/impl/base/pattern.py
testplates/impl/base/structure.py
testplates/impl/base/value.py
testplates/impl/constraints/__init__.py
testplates/impl/constraints/contains.py
testplates/impl/constraints/has_maximum_size.py
testplates/impl/constraints/has_maximum_value.py
testplates/impl/constraints/has_minimum_size.py
testplates/impl/constraints/has_minimum_value.py
testplates/impl/constraints/has_size.py
testplates/impl/constraints/has_size_between.py
testplates/impl/constraints/has_value_between.py
testplates/impl/constraints/is_one_of.py
testplates/impl/constraints/is_permutation_of.py
testplates/impl/constraints/matches_pattern.py
testplates/impl/validators/__init__.py
testplates/impl/validators/boolean.py
testplates/impl/validators/enum.py
testplates/impl/validators/exceptions.py
testplates/impl/validators/integer.py
testplates/impl/validators/mapping.py
testplates/impl/validators/passthrough.py
testplates/impl/validators/sequence.py
testplates/impl/validators/strings.py
testplates/impl/validators/type.py
testplates/impl/validators/union.py
testplates/impl/validators/utils.py
testplates-1.0.0a1.dist-info/LICENSE
testplates-1.0.0a1.dist-info/METADATA
testplates-1.0.0a1.dist-info/WHEEL
testplates-1.0.0a1.dist-info/top_level.txt
testplates-1.0.0a1.dist-info/RECORD
